aicsimageio/__init__.py
aicsimageio/aics_image.py
aicsimageio/constants.py
aicsimageio/dimensions.py
aicsimageio/exceptions.py
aicsimageio/formats.py
aicsimageio/image_container.py
aicsimageio/py.typed
aicsimageio/transforms.py
aicsimageio/types.py
aicsimageio/metadata/__init__.py
aicsimageio/metadata/utils.py
aicsimageio/metadata/czi-to-ome-xslt/xslt/Channels.xsl
aicsimageio/metadata/czi-to-ome-xslt/xslt/CommonTypes.xsl
aicsimageio/metadata/czi-to-ome-xslt/xslt/Constants.xsl
aicsimageio/metadata/czi-to-ome-xslt/xslt/DocumentUser.xsl
aicsimageio/metadata/czi-to-ome-xslt/xslt/Image.xsl
aicsimageio/metadata/czi-to-ome-xslt/xslt/ImagingEnvironment.xsl
aicsimageio/metadata/czi-to-ome-xslt/xslt/Instrument.xsl
aicsimageio/metadata/czi-to-ome-xslt/xslt/ObjectiveSettings.xsl
aicsimageio/metadata/czi-to-ome-xslt/xslt/Pixels.xsl
aicsimageio/metadata/czi-to-ome-xslt/xslt/Plane.xsl
aicsimageio/metadata/czi-to-ome-xslt/xslt/Plate.xsl
aicsimageio/metadata/czi-to-ome-xslt/xslt/StructuredAnnotations.xsl
aicsimageio/metadata/czi-to-ome-xslt/xslt/czi-to-ome.xsl
aicsimageio/readers/__init__.py
aicsimageio/readers/array_like_reader.py
aicsimageio/readers/bfio_reader.py
aicsimageio/readers/bioformats_reader.py
aicsimageio/readers/czi_reader.py
aicsimageio/readers/default_reader.py
aicsimageio/readers/dv_reader.py
aicsimageio/readers/lif_reader.py
aicsimageio/readers/nd2_reader.py
aicsimageio/readers/ome_tiff_reader.py
aicsimageio/readers/ome_zarr_reader.py
aicsimageio/readers/reader.py
aicsimageio/readers/tiff_glob_reader.py
aicsimageio/readers/tiff_reader.py
aicsimageio/readers/sldy_reader/__init__.py
aicsimageio/readers/sldy_reader/sldy_image.py
aicsimageio/utils/__init__.py
aicsimageio/utils/io_utils.py
aicsimageio/writers/__init__.py
aicsimageio/writers/ome_tiff_writer.py
aicsimageio/writers/ome_zarr_writer.py
aicsimageio/writers/timeseries_writer.py
aicsimageio/writers/two_d_writer.py
aicsimageio/writers/writer.py
aicsimageio-4.14.0.dist-info/LICENSE
aicsimageio-4.14.0.dist-info/METADATA
aicsimageio-4.14.0.dist-info/WHEEL
aicsimageio-4.14.0.dist-info/top_level.txt
aicsimageio-4.14.0.dist-info/RECORD
