Metadata-Version: 2.1
Name: aicsimageio
Version: 4.14.0
Summary: Image Reading, Metadata Conversion, and Image Writing for Microscopy Images in Pure Python
Home-page: https://github.com/AllenCellModeling/aicsimageio
Author: Eva Maxfield Brown, Allen Institute for Cell Science
Author-email: evamaxfieldbrown@gmail.com, jamie.sherman@gmail.com, bowdenm@spu.edu
License: BSD-3-Clause
Keywords: imageio,image reading,image writing,metadata,microscopy,allen cell
Classifier: Development Status :: 5 - Production/Stable
Classifier: Intended Audience :: Science/Research
Classifier: Intended Audience :: Developers
Classifier: Intended Audience :: Education
Classifier: License :: OSI Approved :: BSD License
Classifier: Natural Language :: English
Classifier: Programming Language :: Python :: 3.9
Classifier: Programming Language :: Python :: 3.10
Classifier: Programming Language :: Python :: 3.11
Requires-Python: >=3.9
Provides-Extra: setup
Provides-Extra: test
Provides-Extra: dev
Provides-Extra: benchmark
Provides-Extra: base-imageio
Provides-Extra: nd2
Provides-Extra: dv
Provides-Extra: bfio
Provides-Extra: all
License-File: LICENSE
